src/__init__.py
src/data/__init__.py
src/data/camembert_mlm_dataset.py
src/data/make_dataset.py
src/models/__init__.py
src/models/blank_bert_mlm_train.py
src/models/camembert_mlm_ft.py
src/models/utils.py
src/models/xl_net_ft.py
src/resources/__init__.py
src/resources/log_config.ini
mlm_task_for_contextual_embedding-0.38.0.dist-info/LICENSE
mlm_task_for_contextual_embedding-0.38.0.dist-info/METADATA
mlm_task_for_contextual_embedding-0.38.0.dist-info/WHEEL
mlm_task_for_contextual_embedding-0.38.0.dist-info/entry_points.txt
mlm_task_for_contextual_embedding-0.38.0.dist-info/top_level.txt
mlm_task_for_contextual_embedding-0.38.0.dist-info/RECORD
